{"commitInfo":{"timestamp":1675698219174,"operation":"WRITE","operationParameters":{"mode":"Overwrite","partitionBy":"[]"},"readVersion":17,"isolationLevel":"Serializable","isBlindAppend":false,"operationMetrics":{"numFiles":"8","numOutputRows":"7","numOutputBytes":"9475"},"engineInfo":"Apache-Spark/3.3.1 Delta-Lake/2.2.0","txnId":"b99b58d3-2099-48d1-b9ec-c7008534918a"}}
{"add":{"path":"part-00002-3b1047bc-7dc8-40a9-9f9b-a71ac77fb9ff-c000.snappy.parquet","partitionValues":{},"size":1276,"modificationTime":1675698218371,"dataChange":true,"stats":"{\"numRecords\":1,\"minValues\":{\"name\":\"my_test_company_1\",\"id\":1,\"revenue\":100},\"maxValues\":{\"name\":\"my_test_company_1\",\"id\":1,\"revenue\":100},\"nullCount\":{\"name\":0,\"accepted\":0,\"id\":0,\"revenue\":0}}"}}
{"add":{"path":"part-00004-09ec3a6b-1ddc-42e2-97d3-cb4e1b167ef2-c000.snappy.parquet","partitionValues":{},"size":1276,"modificationTime":1675698218371,"dataChange":true,"stats":"{\"numRecords\":1,\"minValues\":{\"name\":\"my_test_company_2\",\"id\":2,\"revenue\":200},\"maxValues\":{\"name\":\"my_test_company_2\",\"id\":2,\"revenue\":200},\"nullCount\":{\"name\":0,\"accepted\":0,\"id\":0,\"revenue\":0}}"}}
{"add":{"path":"part-00006-61df03c7-09d7-407b-bc28-2aa767a5e884-c000.snappy.parquet","partitionValues":{},"size":1276,"modificationTime":1675698218371,"dataChange":true,"stats":"{\"numRecords\":1,\"minValues\":{\"name\":\"my_test_company_3\",\"id\":3,\"revenue\":300},\"maxValues\":{\"name\":\"my_test_company_3\",\"id\":3,\"revenue\":300},\"nullCount\":{\"name\":0,\"accepted\":0,\"id\":0,\"revenue\":0}}"}}
{"add":{"path":"part-00009-e163604d-c5b5-4076-a7e1-b380f772c762-c000.snappy.parquet","partitionValues":{},"size":1275,"modificationTime":1675698218371,"dataChange":true,"stats":"{\"numRecords\":1,\"minValues\":{\"name\":\"my_test_company_4\",\"id\":4,\"revenue\":400},\"maxValues\":{\"name\":\"my_test_company_4\",\"id\":4,\"revenue\":400},\"nullCount\":{\"name\":0,\"accepted\":0,\"id\":0,\"revenue\":0}}"}}
{"add":{"path":"part-00011-a12e169f-cbb7-4b43-ae4c-9a9205e920e0-c000.snappy.parquet","partitionValues":{},"size":1276,"modificationTime":1675698218371,"dataChange":true,"stats":"{\"numRecords\":1,\"minValues\":{\"name\":\"my_test_company_5\",\"id\":5,\"revenue\":80},\"maxValues\":{\"name\":\"my_test_company_5\",\"id\":5,\"revenue\":80},\"nullCount\":{\"name\":0,\"accepted\":0,\"id\":0,\"revenue\":0}}"}}
{"add":{"path":"part-00013-75ba18b8-353a-4e62-a21e-22c8ab5c9422-c000.snappy.parquet","partitionValues":{},"size":1276,"modificationTime":1675698218371,"dataChange":true,"stats":"{\"numRecords\":1,\"minValues\":{\"name\":\"my_test_company_6\",\"id\":6,\"revenue\":90},\"maxValues\":{\"name\":\"my_test_company_6\",\"id\":6,\"revenue\":90},\"nullCount\":{\"name\":0,\"accepted\":0,\"id\":0,\"revenue\":0}}"}}
{"add":{"path":"part-00015-dd7f69f2-cfb7-45eb-980b-d8b8afe5ecee-c000.snappy.parquet","partitionValues":{},"size":1276,"modificationTime":1675698218371,"dataChange":true,"stats":"{\"numRecords\":1,\"minValues\":{\"name\":\"my_test_company_7\",\"id\":7,\"revenue\":95},\"maxValues\":{\"name\":\"my_test_company_7\",\"id\":7,\"revenue\":95},\"nullCount\":{\"name\":0,\"accepted\":0,\"id\":0,\"revenue\":0}}"}}
{"remove":{"path":"part-00002-3203c254-f883-4998-ac79-88948ba29f74-c000.snappy.parquet","deletionTimestamp":1675698219127,"dataChange":true,"extendedFileMetadata":true,"partitionValues":{},"size":1276}}
{"remove":{"path":"part-00013-dde82aea-933d-4e35-9b07-e36149647f53-c000.snappy.parquet","deletionTimestamp":1675698219127,"dataChange":true,"extendedFileMetadata":true,"partitionValues":{},"size":1276}}
{"remove":{"path":"part-00006-98016228-92dd-492a-9496-4be87c0697c3-c000.snappy.parquet","deletionTimestamp":1675698219127,"dataChange":true,"extendedFileMetadata":true,"partitionValues":{},"size":1276}}
{"remove":{"path":"part-00009-bb350908-4192-4b74-8c76-f167b69be7b9-c000.snappy.parquet","deletionTimestamp":1675698219127,"dataChange":true,"extendedFileMetadata":true,"partitionValues":{},"size":1275}}
{"remove":{"path":"part-00011-f98798d5-8abf-42a7-83d4-a1f266e462e6-c000.snappy.parquet","deletionTimestamp":1675698219127,"dataChange":true,"extendedFileMetadata":true,"partitionValues":{},"size":1276}}
{"remove":{"path":"part-00004-b875b63b-4d8e-4e8b-9a94-62c1a38b09ea-c000.snappy.parquet","deletionTimestamp":1675698219127,"dataChange":true,"extendedFileMetadata":true,"partitionValues":{},"size":1276}}
{"remove":{"path":"part-00015-0b139043-c969-4518-9c93-99b2e77750d5-c000.snappy.parquet","deletionTimestamp":1675698219127,"dataChange":true,"extendedFileMetadata":true,"partitionValues":{},"size":1276}}
